<annotation>
	<folder>images</folder>
	<filename>30th_st6.jpg</filename>
	<path>D:\Courses\Data Mining and Knowledge CS-653\Road_feature_train\images\30th_st6.jpg</path>
	<source>
		<database>Unknown</database>
	</source>
	<size>
		<width>640</width>
		<height>640</height>
		<depth>3</depth>
	</size>
	<segmented>0</segmented>
	<object>
		<name>road line</name>
		<pose>Unspecified</pose>
		<truncated>0</truncated>
		<difficult>0</difficult>
		<bndbox>
			<xmin>374</xmin>
			<ymin>484</ymin>
			<xmax>423</xmax>
			<ymax>531</ymax>
		</bndbox>
	</object>
	<object>
		<name>road line</name>
		<pose>Unspecified</pose>
		<truncated>0</truncated>
		<difficult>0</difficult>
		<bndbox>
			<xmin>534</xmin>
			<ymin>518</ymin>
			<xmax>607</xmax>
			<ymax>564</ymax>
		</bndbox>
	</object>
	<object>
		<name>road line</name>
		<pose>Unspecified</pose>
		<truncated>0</truncated>
		<difficult>0</difficult>
		<bndbox>
			<xmin>397</xmin>
			<ymin>456</ymin>
			<xmax>425</xmax>
			<ymax>472</ymax>
		</bndbox>
	</object>
</annotation>
